tuya_api/__init__.py
tuya_api/__version__.py
tuya_api/core.py
tuya_api-1.0.5.dist-info/LICENSE
tuya_api-1.0.5.dist-info/METADATA
tuya_api-1.0.5.dist-info/WHEEL
tuya_api-1.0.5.dist-info/top_level.txt
tuya_api-1.0.5.dist-info/RECORD
