Metadata-Version: 2.1
Name: tuya-api
Version: 1.0.5
Summary: Make easier to use Tuya’s API.
Home-page: https://github.com/AD-feiben/tuya_api
Author: Feiben
Author-email: feiben.dev@gmail.com
License: MIT
Platform: UNKNOWN
Classifier: License :: OSI Approved :: MIT License
Classifier: Programming Language :: Python
Classifier: Programming Language :: Python :: 3
Classifier: Programming Language :: Python :: 3.6
Classifier: Programming Language :: Python :: Implementation :: CPython
Classifier: Programming Language :: Python :: Implementation :: PyPy
Requires-Python: >=3.5.0
Requires-Dist: tornado
